concurrent_iterator/__init__.py
concurrent_iterator/connections.py
concurrent_iterator/dummy.py
concurrent_iterator/process.py
concurrent_iterator/thread.py
concurrent_iterator/utils.py
concurrent_iterator-0.3.0.dist-info/LICENSE
concurrent_iterator-0.3.0.dist-info/METADATA
concurrent_iterator-0.3.0.dist-info/WHEEL
concurrent_iterator-0.3.0.dist-info/top_level.txt
concurrent_iterator-0.3.0.dist-info/zip-safe
concurrent_iterator-0.3.0.dist-info/RECORD
