Metadata-Version: 2.1
Name: concurrent-iterator
Version: 0.3.0
Summary: Classes to run producers (iterators) and consumers (coroutines) in a background thread/process.
Home-page: https://github.com/jruere/concurrent-iterator
Author: Javier Ruere
Author-email: javier@ruere.com.ar
License: LGPLv3
Keywords: concurrency parallelism iterator iterable pipeline
Platform: POSIX
Classifier: Development Status :: 4 - Beta
Classifier: Intended Audience :: Developers
Classifier: License :: OSI Approved :: GNU Lesser General Public License v3 or later (LGPLv3+)
Classifier: Programming Language :: Python :: 2
Classifier: Programming Language :: Python :: 2.7
Classifier: Programming Language :: Python :: 3
Classifier: Programming Language :: Python :: 3.6
Classifier: Programming Language :: Python :: 3.7
Classifier: Programming Language :: Python :: 3.8
Classifier: Programming Language :: Python :: 3.9
Classifier: Programming Language :: Python :: 3.10
Classifier: Programming Language :: Python :: Implementation :: CPython
Classifier: Programming Language :: Python :: Implementation :: PyPy
Classifier: Operating System :: POSIX
Classifier: Topic :: Software Development :: Libraries :: Python Modules
License-File: LICENSE
Requires-Dist: decorator
